__init__.py
perform_draw.py
modules/makedrawverify.py
modules/selector.py
perform_draw-0.0.1.dist-info/LICENCE
perform_draw-0.0.1.dist-info/METADATA
perform_draw-0.0.1.dist-info/WHEEL
perform_draw-0.0.1.dist-info/top_level.txt
perform_draw-0.0.1.dist-info/RECORD
