Metadata-Version: 2.1
Name: perform-draw
Version: 0.0.1
Summary: To return a lsit of randomly drawn numbers from a user defined list of numbers.
Classifier: Programming Language :: Python :: 3
Classifier: Programming Language :: Python :: 3.10
Classifier: License :: OSI Approved :: GNU General Public License v3 or later (GPLv3+)
Classifier: Operating System :: OS Independent
Classifier: Development Status :: 3 - Alpha
Classifier: Natural Language :: English
Classifier: Topic :: Utilities
License-File: LICENCE
